mypackage/Scrap_and_predict_accounts.py
mypackage/__init__.py
mypackage/api.py
mypackage/classfication.py
mypackage/config.py
mypackage/data_processing.py
mypackage/facebook_scraping.py
mypackage/useful_function.py
mypackage/pages/Train_Model.py
mypackage/pages/__init__.py
tests/__init__.py
tests/classfication.py
tests/test_classfication.py
facebook_scrapper_ml-0.1.dist-info/LICENSE.txt
facebook_scrapper_ml-0.1.dist-info/METADATA
facebook_scrapper_ml-0.1.dist-info/WHEEL
facebook_scrapper_ml-0.1.dist-info/top_level.txt
facebook_scrapper_ml-0.1.dist-info/RECORD
