Metadata-Version: 2.1
Name: facebook_scrapper_ml
Version: 0.1
Summary: Facebook Scrapper
Classifier: Intended Audience :: Education
Classifier: Development Status :: 4 - Beta
Classifier: Operating System :: OS Independent
Requires-Python: >=3.12
License-File: LICENSE.txt
Requires-Dist: joblib
Requires-Dist: numpy
Requires-Dist: pandas
Requires-Dist: scikit-learn
Requires-Dist: scipy
Requires-Dist: selenium
Requires-Dist: streamlit
Requires-Dist: webdriver-manager
Requires-Dist: matplotlib
Requires-Dist: fastapi
Requires-Dist: pydantic
Requires-Dist: uvicorn
